MANIFEST.in
README.rst
setup.py
django_simple_feedback.egg-info/PKG-INFO
django_simple_feedback.egg-info/SOURCES.txt
django_simple_feedback.egg-info/dependency_links.txt
django_simple_feedback.egg-info/top_level.txt
example_feedback/__init__.py
example_feedback/manage.py
example_feedback/settings.py
example_feedback/urls.py
feedback/__init__.py
feedback/admin.py
feedback/app_settings.py
feedback/models.py
feedback/tests.py
feedback/urls.py
feedback/views.py
feedback/migrations/0001_initial.py
feedback/migrations/0002_auto__add_votes__del_field_feedback_user.py
feedback/migrations/0003_auto__chg_field_votes_feedback.py
feedback/migrations/0004_auto__chg_field_votes_feedback.py
feedback/migrations/0005_auto__del_votes__add_vote.py
feedback/migrations/0006_auto__add_field_feedback_path.py
feedback/migrations/0007_auto__add_field_feedback_user__add_field_feedback_added.py
feedback/migrations/0008_fill_in_user.py
feedback/migrations/0009_auto__add_field_feedback_extra.py
feedback/migrations/__init__.py
feedback/static/feedback/css/feedback.css
feedback/static/feedback/img/close_icon.jpg
feedback/static/feedback/img/down.png
feedback/static/feedback/img/feedback.png
feedback/static/feedback/img/up.png
feedback/static/feedback/img/user.png
feedback/static/feedback/js/feedback.js
feedback/static/feedback/js/jquery-1.4.2.min.js
feedback/static/feedback/js/jquery-1.7.1.min.js
feedback/templates/feedback/base.html
feedback/templates/feedback/feedbacks.html
feedback/templatetags/__init__.py
feedback/templatetags/feedback_tags.py