Metadata-Version: 1.1
Name: django-simple-feedback
Version: 0.2.10
Summary: Django application that allows you to easily get user
Home-page: http://github.com/Narsil/django-simple-feedback
Author: Nicolas Patry
Author-email: nicolas.patry@student.ecp.fr
License: UNKNOWN
Download-URL: http://github.com/Narsil/django-simple-feedback
Keywords: django feedback bugs suggestions
Platform: UNKNOWN
Classifier: Development Status :: 4 - Beta
Classifier: Intended Audience :: Developers
Classifier: License :: OSI Approved :: GNU Library or Lesser General Public License (LGPL)
Classifier: Topic :: Software Development :: Libraries :: Python Modules
Classifier: Environment :: Web Environment
Classifier: Topic :: Internet
Classifier: Operating System :: OS Independent
Classifier: Programming Language :: Python
Classifier: Framework :: Django
